[
  {
    "config": {
      "size_hidden_layers": [
        16,
        8
      ],
      "input_dim": 9,
      "output_dim": 2,
      "activation": [
        "tanh",
        "sigmoid"
      ],
      "learning_rate": 0.001,
      "momentum": 0.0,
      "regularization": [
        "l2",
        1e-06
      ],
      "monitor": "Val_MEE",
      "early_stopping": [
        1e-05,
        200
      ],
      "weights_initialization": [
        "FanOut",
        0
      ],
      "max_epoch": 2000,
      "minibatch_size": 8,
      "decay": "none"
    },
    "mean": 1.4402436017990112,
    "std": 0.0
  },
  {
    "config": {
      "size_hidden_layers": [
        16,
        8
      ],
      "input_dim": 9,
      "output_dim": 2,
      "activation": [
        "tanh",
        "sigmoid"
      ],
      "learning_rate": 0.001,
      "momentum": 0.0,
      "regularization": [
        "l2",
        1e-07
      ],
      "monitor": "Val_MEE",
      "early_stopping": [
        1e-05,
        200
      ],
      "weights_initialization": [
        "FanOut",
        0
      ],
      "max_epoch": 2000,
      "minibatch_size": 8,
      "decay": "none"
    },
    "mean": 1.454525351524353,
    "std": 0.0
  },
  {
    "config": {
      "size_hidden_layers": [
        16,
        8
      ],
      "input_dim": 9,
      "output_dim": 2,
      "activation": [
        "tanh",
        "sigmoid"
      ],
      "learning_rate": 0.001,
      "momentum": 0.0,
      "regularization": "none",
      "monitor": "Val_MEE",
      "early_stopping": [
        1e-05,
        200
      ],
      "weights_initialization": [
        "FanOut",
        0
      ],
      "max_epoch": 2000,
      "minibatch_size": 8,
      "decay": "none"
    },
    "mean": 1.457968831062317,
    "std": 0.0
  },
  {
    "config": {
      "size_hidden_layers": [
        8,
        8
      ],
      "input_dim": 9,
      "output_dim": 2,
      "activation": "tanh",
      "learning_rate": 0.01,
      "momentum": 0.0,
      "regularization": [
        "l2",
        1e-06
      ],
      "monitor": "Val_MEE",
      "early_stopping": [
        1e-05,
        200
      ],
      "weights_initialization": [
        "Uniform",
        -0.5,
        0.5,
        0
      ],
      "max_epoch": 2000,
      "minibatch_size": 16,
      "decay": [
        "linear",
        0.1,
        8
      ]
    },
    "mean": 1.47511625289917,
    "std": 0.0
  },
  {
    "config": {
      "size_hidden_layers": [
        8,
        8
      ],
      "input_dim": 9,
      "output_dim": 2,
      "activation": "tanh",
      "learning_rate": 0.01,
      "momentum": 0.0,
      "regularization": [
        "l2",
        1e-07
      ],
      "monitor": "Val_MEE",
      "early_stopping": [
        1e-05,
        200
      ],
      "weights_initialization": [
        "Uniform",
        -0.5,
        0.5,
        0
      ],
      "max_epoch": 2000,
      "minibatch_size": 16,
      "decay": [
        "linear",
        0.1,
        8
      ]
    },
    "mean": 1.4757746458053589,
    "std": 0.0
  },
  {
    "config": {
      "size_hidden_layers": [
        8,
        8
      ],
      "input_dim": 9,
      "output_dim": 2,
      "activation": "tanh",
      "learning_rate": 0.01,
      "momentum": 0.0,
      "regularization": "none",
      "monitor": "Val_MEE",
      "early_stopping": [
        1e-05,
        200
      ],
      "weights_initialization": [
        "Uniform",
        -0.5,
        0.5,
        0
      ],
      "max_epoch": 2000,
      "minibatch_size": 16,
      "decay": [
        "linear",
        0.1,
        8
      ]
    },
    "mean": 1.4758529663085938,
    "std": 0.0
  },
  {
    "config": {
      "size_hidden_layers": [
        16,
        8
      ],
      "input_dim": 9,
      "output_dim": 2,
      "activation": [
        "tanh",
        "sigmoid"
      ],
      "learning_rate": 0.01,
      "momentum": 0.0,
      "regularization": [
        "l2",
        1e-06
      ],
      "monitor": "Val_MEE",
      "early_stopping": [
        1e-05,
        200
      ],
      "weights_initialization": [
        "FanOut",
        0
      ],
      "max_epoch": 2000,
      "minibatch_size": 8,
      "decay": "none"
    },
    "mean": 1.4769195318222046,
    "std": 0.0
  },
  {
    "config": {
      "size_hidden_layers": [
        8,
        8
      ],
      "input_dim": 9,
      "output_dim": 2,
      "activation": "sigmoid",
      "learning_rate": 0.01,
      "momentum": 0.0,
      "regularization": [
        "l2",
        1e-06
      ],
      "monitor": "Val_MEE",
      "early_stopping": [
        1e-05,
        200
      ],
      "weights_initialization": [
        "Uniform",
        -0.5,
        0.5,
        0
      ],
      "max_epoch": 2000,
      "minibatch_size": 8,
      "decay": "none"
    },
    "mean": 1.4774612188339233,
    "std": 0.0
  },
  {
    "config": {
      "size_hidden_layers": [
        8,
        8
      ],
      "input_dim": 9,
      "output_dim": 2,
      "activation": "tanh",
      "learning_rate": 0.01,
      "momentum": 0.0,
      "regularization": [
        "l2",
        1e-06
      ],
      "monitor": "Val_MEE",
      "early_stopping": [
        1e-05,
        200
      ],
      "weights_initialization": [
        "Uniform",
        -0.5,
        0.5,
        0
      ],
      "max_epoch": 2000,
      "minibatch_size": 16,
      "decay": "none"
    },
    "mean": 1.4775091409683228,
    "std": 0.0
  },
  {
    "config": {
      "size_hidden_layers": [
        8,
        8
      ],
      "input_dim": 9,
      "output_dim": 2,
      "activation": "tanh",
      "learning_rate": 0.01,
      "momentum": 0.0,
      "regularization": [
        "l2",
        1e-07
      ],
      "monitor": "Val_MEE",
      "early_stopping": [
        1e-05,
        200
      ],
      "weights_initialization": [
        "Uniform",
        -0.5,
        0.5,
        0
      ],
      "max_epoch": 2000,
      "minibatch_size": 16,
      "decay": "none"
    },
    "mean": 1.4781628847122192,
    "std": 0.0
  },
  {
    "config": {
      "size_hidden_layers": [
        8,
        8
      ],
      "input_dim": 9,
      "output_dim": 2,
      "activation": "tanh",
      "learning_rate": 0.01,
      "momentum": 0.0,
      "regularization": "none",
      "monitor": "Val_MEE",
      "early_stopping": [
        1e-05,
        200
      ],
      "weights_initialization": [
        "Uniform",
        -0.5,
        0.5,
        0
      ],
      "max_epoch": 2000,
      "minibatch_size": 16,
      "decay": "none"
    },
    "mean": 1.4782403707504272,
    "std": 0.0
  },
  {
    "config": {
      "size_hidden_layers": [
        16,
        8
      ],
      "input_dim": 9,
      "output_dim": 2,
      "activation": [
        "sigmoid",
        "tanh"
      ],
      "learning_rate": 0.001,
      "momentum": 0.4,
      "regularization": "none",
      "monitor": "Val_MEE",
      "early_stopping": [
        1e-05,
        200
      ],
      "weights_initialization": [
        "FanOut",
        0
      ],
      "max_epoch": 2000,
      "minibatch_size": 8,
      "decay": [
        "linear",
        0.1,
        8
      ]
    },
    "mean": 1.4798756837844849,
    "std": 0.0
  },
  {
    "config": {
      "size_hidden_layers": [
        8,
        8
      ],
      "input_dim": 9,
      "output_dim": 2,
      "activation": "sigmoid",
      "learning_rate": 0.01,
      "momentum": 0.0,
      "regularization": [
        "l2",
        1e-07
      ],
      "monitor": "Val_MEE",
      "early_stopping": [
        1e-05,
        200
      ],
      "weights_initialization": [
        "Uniform",
        -0.5,
        0.5,
        0
      ],
      "max_epoch": 2000,
      "minibatch_size": 8,
      "decay": "none"
    },
    "mean": 1.4798907041549683,
    "std": 0.0
  },
  {
    "config": {
      "size_hidden_layers": [
        16,
        8
      ],
      "input_dim": 9,
      "output_dim": 2,
      "activation": [
        "sigmoid",
        "tanh"
      ],
      "learning_rate": 0.001,
      "momentum": 0.4,
      "regularization": [
        "l2",
        1e-07
      ],
      "monitor": "Val_MEE",
      "early_stopping": [
        1e-05,
        200
      ],
      "weights_initialization": [
        "FanOut",
        0
      ],
      "max_epoch": 2000,
      "minibatch_size": 8,
      "decay": [
        "linear",
        0.1,
        8
      ]
    },
    "mean": 1.480051875114441,
    "std": 0.0
  },
  {
    "config": {
      "size_hidden_layers": [
        8,
        8
      ],
      "input_dim": 9,
      "output_dim": 2,
      "activation": "sigmoid",
      "learning_rate": 0.01,
      "momentum": 0.0,
      "regularization": "none",
      "monitor": "Val_MEE",
      "early_stopping": [
        1e-05,
        200
      ],
      "weights_initialization": [
        "Uniform",
        -0.5,
        0.5,
        0
      ],
      "max_epoch": 2000,
      "minibatch_size": 8,
      "decay": "none"
    },
    "mean": 1.480238676071167,
    "std": 0.0
  },
  {
    "config": {
      "size_hidden_layers": [
        8,
        4
      ],
      "input_dim": 9,
      "output_dim": 2,
      "activation": [
        "sigmoid",
        "tanh"
      ],
      "learning_rate": 0.001,
      "momentum": 0.8,
      "regularization": [
        "l2",
        1e-06
      ],
      "monitor": "Val_MEE",
      "early_stopping": [
        1e-05,
        200
      ],
      "weights_initialization": [
        "FanOut",
        0
      ],
      "max_epoch": 2000,
      "minibatch_size": 8,
      "decay": "none"
    },
    "mean": 1.4802786111831665,
    "std": 0.0
  },
  {
    "config": {
      "size_hidden_layers": [
        16,
        8
      ],
      "input_dim": 9,
      "output_dim": 2,
      "activation": [
        "tanh",
        "sigmoid"
      ],
      "learning_rate": 0.001,
      "momentum": 0.8,
      "regularization": [
        "l2",
        1e-06
      ],
      "monitor": "Val_MEE",
      "early_stopping": [
        1e-05,
        200
      ],
      "weights_initialization": [
        "FanOut",
        0
      ],
      "max_epoch": 2000,
      "minibatch_size": 16,
      "decay": [
        "linear",
        0.1,
        8
      ]
    },
    "mean": 1.4807084798812866,
    "std": 0.0
  },
  {
    "config": {
      "size_hidden_layers": [
        16,
        8
      ],
      "input_dim": 9,
      "output_dim": 2,
      "activation": [
        "tanh",
        "sigmoid"
      ],
      "learning_rate": 0.01,
      "momentum": 0.0,
      "regularization": [
        "l2",
        1e-07
      ],
      "monitor": "Val_MEE",
      "early_stopping": [
        1e-05,
        200
      ],
      "weights_initialization": [
        "FanOut",
        0
      ],
      "max_epoch": 2000,
      "minibatch_size": 8,
      "decay": "none"
    },
    "mean": 1.4808741807937622,
    "std": 0.0
  },
  {
    "config": {
      "size_hidden_layers": [
        16,
        8
      ],
      "input_dim": 9,
      "output_dim": 2,
      "activation": [
        "tanh",
        "sigmoid"
      ],
      "learning_rate": 0.001,
      "momentum": 0.8,
      "regularization": [
        "l2",
        1e-06
      ],
      "monitor": "Val_MEE",
      "early_stopping": [
        1e-05,
        200
      ],
      "weights_initialization": [
        "FanOut",
        0
      ],
      "max_epoch": 2000,
      "minibatch_size": 8,
      "decay": [
        "linear",
        0.1,
        8
      ]
    },
    "mean": 1.4809774160385132,
    "std": 0.0
  },
  {
    "config": {
      "size_hidden_layers": [
        8,
        4
      ],
      "input_dim": 9,
      "output_dim": 2,
      "activation": [
        "sigmoid",
        "tanh"
      ],
      "learning_rate": 0.001,
      "momentum": 0.8,
      "regularization": [
        "l2",
        1e-07
      ],
      "monitor": "Val_MEE",
      "early_stopping": [
        1e-05,
        200
      ],
      "weights_initialization": [
        "FanOut",
        0
      ],
      "max_epoch": 2000,
      "minibatch_size": 8,
      "decay": "none"
    },
    "mean": 1.4810197353363037,
    "std": 0.0
  },
  {
    "config": {
      "size_hidden_layers": [
        8,
        4
      ],
      "input_dim": 9,
      "output_dim": 2,
      "activation": [
        "sigmoid",
        "tanh"
      ],
      "learning_rate": 0.001,
      "momentum": 0.8,
      "regularization": "none",
      "monitor": "Val_MEE",
      "early_stopping": [
        1e-05,
        200
      ],
      "weights_initialization": [
        "FanOut",
        0
      ],
      "max_epoch": 2000,
      "minibatch_size": 8,
      "decay": "none"
    },
    "mean": 1.4810599088668823,
    "std": 0.0
  },
  {
    "config": {
      "size_hidden_layers": [
        16,
        8
      ],
      "input_dim": 9,
      "output_dim": 2,
      "activation": [
        "tanh",
        "sigmoid"
      ],
      "learning_rate": 0.01,
      "momentum": 0.0,
      "regularization": "none",
      "monitor": "Val_MEE",
      "early_stopping": [
        1e-05,
        200
      ],
      "weights_initialization": [
        "FanOut",
        0
      ],
      "max_epoch": 2000,
      "minibatch_size": 8,
      "decay": "none"
    },
    "mean": 1.4812860488891602,
    "std": 0.0
  },
  {
    "config": {
      "size_hidden_layers": [
        16,
        8
      ],
      "input_dim": 9,
      "output_dim": 2,
      "activation": [
        "tanh",
        "sigmoid"
      ],
      "learning_rate": 0.001,
      "momentum": 0.8,
      "regularization": [
        "l2",
        1e-06
      ],
      "monitor": "Val_MEE",
      "early_stopping": [
        1e-05,
        200
      ],
      "weights_initialization": [
        "FanOut",
        0
      ],
      "max_epoch": 2000,
      "minibatch_size": 16,
      "decay": "none"
    },
    "mean": 1.481345772743225,
    "std": 0.0
  },
  {
    "config": {
      "size_hidden_layers": [
        16,
        8
      ],
      "input_dim": 9,
      "output_dim": 2,
      "activation": [
        "sigmoid",
        "tanh"
      ],
      "learning_rate": 0.001,
      "momentum": 0.4,
      "regularization": "none",
      "monitor": "Val_MEE",
      "early_stopping": [
        1e-05,
        200
      ],
      "weights_initialization": [
        "FanOut",
        0
      ],
      "max_epoch": 2000,
      "minibatch_size": 8,
      "decay": "none"
    },
    "mean": 1.4819649457931519,
    "std": 0.0
  },
  {
    "config": {
      "size_hidden_layers": [
        16,
        8
      ],
      "input_dim": 9,
      "output_dim": 2,
      "activation": [
        "sigmoid",
        "tanh"
      ],
      "learning_rate": 0.001,
      "momentum": 0.4,
      "regularization": [
        "l2",
        1e-07
      ],
      "monitor": "Val_MEE",
      "early_stopping": [
        1e-05,
        200
      ],
      "weights_initialization": [
        "FanOut",
        0
      ],
      "max_epoch": 2000,
      "minibatch_size": 8,
      "decay": "none"
    },
    "mean": 1.4820135831832886,
    "std": 0.0
  },
  {
    "config": {
      "size_hidden_layers": [
        8,
        8
      ],
      "input_dim": 9,
      "output_dim": 2,
      "activation": [
        "sigmoid",
        "tanh"
      ],
      "learning_rate": 0.01,
      "momentum": 0.8,
      "regularization": [
        "l2",
        1e-06
      ],
      "monitor": "Val_MEE",
      "early_stopping": [
        1e-05,
        200
      ],
      "weights_initialization": [
        "Uniform",
        -0.5,
        0.5,
        0
      ],
      "max_epoch": 2000,
      "minibatch_size": 16,
      "decay": "none"
    },
    "mean": 1.4822527170181274,
    "std": 0.0
  },
  {
    "config": {
      "size_hidden_layers": [
        16,
        8
      ],
      "input_dim": 9,
      "output_dim": 2,
      "activation": [
        "tanh",
        "sigmoid"
      ],
      "learning_rate": 0.001,
      "momentum": 0.8,
      "regularization": [
        "l2",
        1e-07
      ],
      "monitor": "Val_MEE",
      "early_stopping": [
        1e-05,
        200
      ],
      "weights_initialization": [
        "FanOut",
        0
      ],
      "max_epoch": 2000,
      "minibatch_size": 16,
      "decay": [
        "linear",
        0.1,
        8
      ]
    },
    "mean": 1.48225736618042,
    "std": 0.0
  },
  {
    "config": {
      "size_hidden_layers": [
        16,
        8
      ],
      "input_dim": 9,
      "output_dim": 2,
      "activation": [
        "tanh",
        "sigmoid"
      ],
      "learning_rate": 0.001,
      "momentum": 0.8,
      "regularization": "none",
      "monitor": "Val_MEE",
      "early_stopping": [
        1e-05,
        200
      ],
      "weights_initialization": [
        "FanOut",
        0
      ],
      "max_epoch": 2000,
      "minibatch_size": 16,
      "decay": [
        "linear",
        0.1,
        8
      ]
    },
    "mean": 1.482452630996704,
    "std": 0.0
  },
  {
    "config": {
      "size_hidden_layers": [
        16,
        8
      ],
      "input_dim": 9,
      "output_dim": 2,
      "activation": [
        "sigmoid",
        "tanh"
      ],
      "learning_rate": 0.001,
      "momentum": 0.8,
      "regularization": "none",
      "monitor": "Val_MEE",
      "early_stopping": [
        1e-05,
        200
      ],
      "weights_initialization": [
        "FanOut",
        0
      ],
      "max_epoch": 2000,
      "minibatch_size": 16,
      "decay": "none"
    },
    "mean": 1.4827297925949097,
    "std": 0.0
  },
  {
    "config": {
      "size_hidden_layers": [
        16,
        8
      ],
      "input_dim": 9,
      "output_dim": 2,
      "activation": [
        "tanh",
        "sigmoid"
      ],
      "learning_rate": 0.001,
      "momentum": 0.8,
      "regularization": [
        "l2",
        1e-07
      ],
      "monitor": "Val_MEE",
      "early_stopping": [
        1e-05,
        200
      ],
      "weights_initialization": [
        "FanOut",
        0
      ],
      "max_epoch": 2000,
      "minibatch_size": 16,
      "decay": "none"
    },
    "mean": 1.482904076576233,
    "std": 0.0
  },
  {
    "config": {
      "size_hidden_layers": [
        16,
        8
      ],
      "input_dim": 9,
      "output_dim": 2,
      "activation": [
        "tanh",
        "sigmoid"
      ],
      "learning_rate": 0.001,
      "momentum": 0.0,
      "regularization": [
        "l2",
        1e-07
      ],
      "monitor": "Val_MEE",
      "early_stopping": [
        1e-05,
        200
      ],
      "weights_initialization": [
        "FanOut",
        0
      ],
      "max_epoch": 2000,
      "minibatch_size": 8,
      "decay": [
        "linear",
        0.1,
        8
      ]
    },
    "mean": 1.4830195903778076,
    "std": 0.0
  },
  {
    "config": {
      "size_hidden_layers": [
        16,
        8
      ],
      "input_dim": 9,
      "output_dim": 2,
      "activation": [
        "tanh",
        "sigmoid"
      ],
      "learning_rate": 0.01,
      "momentum": 0.0,
      "regularization": [
        "l2",
        1e-06
      ],
      "monitor": "Val_MEE",
      "early_stopping": [
        1e-05,
        200
      ],
      "weights_initialization": [
        "FanOut",
        0
      ],
      "max_epoch": 2000,
      "minibatch_size": 8,
      "decay": [
        "linear",
        0.1,
        8
      ]
    },
    "mean": 1.4830487966537476,
    "std": 0.0
  },
  {
    "config": {
      "size_hidden_layers": [
        16,
        8
      ],
      "input_dim": 9,
      "output_dim": 2,
      "activation": [
        "sigmoid",
        "tanh"
      ],
      "learning_rate": 0.001,
      "momentum": 0.8,
      "regularization": [
        "l2",
        1e-07
      ],
      "monitor": "Val_MEE",
      "early_stopping": [
        1e-05,
        200
      ],
      "weights_initialization": [
        "FanOut",
        0
      ],
      "max_epoch": 2000,
      "minibatch_size": 16,
      "decay": "none"
    },
    "mean": 1.4830820560455322,
    "std": 0.0
  },
  {
    "config": {
      "size_hidden_layers": [
        16,
        8
      ],
      "input_dim": 9,
      "output_dim": 2,
      "activation": [
        "tanh",
        "sigmoid"
      ],
      "learning_rate": 0.001,
      "momentum": 0.8,
      "regularization": "none",
      "monitor": "Val_MEE",
      "early_stopping": [
        1e-05,
        200
      ],
      "weights_initialization": [
        "FanOut",
        0
      ],
      "max_epoch": 2000,
      "minibatch_size": 16,
      "decay": "none"
    },
    "mean": 1.483099102973938,
    "std": 0.0
  },
  {
    "config": {
      "size_hidden_layers": [
        16,
        8
      ],
      "input_dim": 9,
      "output_dim": 2,
      "activation": [
        "tanh",
        "sigmoid"
      ],
      "learning_rate": 0.01,
      "momentum": 0.0,
      "regularization": [
        "l2",
        1e-06
      ],
      "monitor": "Val_MEE",
      "early_stopping": [
        1e-05,
        200
      ],
      "weights_initialization": [
        "FanOut",
        0
      ],
      "max_epoch": 2000,
      "minibatch_size": 16,
      "decay": [
        "linear",
        0.1,
        8
      ]
    },
    "mean": 1.4832158088684082,
    "std": 0.0
  },
  {
    "config": {
      "size_hidden_layers": [
        8,
        4
      ],
      "input_dim": 9,
      "output_dim": 2,
      "activation": [
        "sigmoid",
        "tanh"
      ],
      "learning_rate": 0.001,
      "momentum": 0.8,
      "regularization": [
        "l2",
        1e-06
      ],
      "monitor": "Val_MEE",
      "early_stopping": [
        1e-05,
        200
      ],
      "weights_initialization": [
        "FanOut",
        0
      ],
      "max_epoch": 2000,
      "minibatch_size": 8,
      "decay": [
        "linear",
        0.1,
        8
      ]
    },
    "mean": 1.4832630157470703,
    "std": 0.0
  },
  {
    "config": {
      "size_hidden_layers": [
        16,
        8
      ],
      "input_dim": 9,
      "output_dim": 2,
      "activation": [
        "sigmoid",
        "tanh"
      ],
      "learning_rate": 0.001,
      "momentum": 0.4,
      "regularization": [
        "l2",
        1e-06
      ],
      "monitor": "Val_MEE",
      "early_stopping": [
        1e-05,
        200
      ],
      "weights_initialization": [
        "FanOut",
        0
      ],
      "max_epoch": 2000,
      "minibatch_size": 8,
      "decay": [
        "linear",
        0.1,
        8
      ]
    },
    "mean": 1.4834136962890625,
    "std": 0.0
  },
  {
    "config": {
      "size_hidden_layers": [
        16,
        8
      ],
      "input_dim": 9,
      "output_dim": 2,
      "activation": [
        "tanh",
        "sigmoid"
      ],
      "learning_rate": 0.001,
      "momentum": 0.0,
      "regularization": "none",
      "monitor": "Val_MEE",
      "early_stopping": [
        1e-05,
        200
      ],
      "weights_initialization": [
        "FanOut",
        0
      ],
      "max_epoch": 2000,
      "minibatch_size": 8,
      "decay": [
        "linear",
        0.1,
        8
      ]
    },
    "mean": 1.483540654182434,
    "std": 0.0
  },
  {
    "config": {
      "size_hidden_layers": [
        8,
        8
      ],
      "input_dim": 9,
      "output_dim": 2,
      "activation": "sigmoid",
      "learning_rate": 0.01,
      "momentum": 0.0,
      "regularization": [
        "l2",
        1e-06
      ],
      "monitor": "Val_MEE",
      "early_stopping": [
        1e-05,
        200
      ],
      "weights_initialization": [
        "Uniform",
        -0.5,
        0.5,
        0
      ],
      "max_epoch": 2000,
      "minibatch_size": 8,
      "decay": [
        "linear",
        0.1,
        8
      ]
    },
    "mean": 1.4835485219955444,
    "std": 0.0
  },
  {
    "config": {
      "size_hidden_layers": [
        16,
        8
      ],
      "input_dim": 9,
      "output_dim": 2,
      "activation": [
        "sigmoid",
        "tanh"
      ],
      "learning_rate": 0.001,
      "momentum": 0.4,
      "regularization": [
        "l2",
        1e-06
      ],
      "monitor": "Val_MEE",
      "early_stopping": [
        1e-05,
        200
      ],
      "weights_initialization": [
        "FanOut",
        0
      ],
      "max_epoch": 2000,
      "minibatch_size": 8,
      "decay": "none"
    },
    "mean": 1.483609914779663,
    "std": 0.0
  },
  {
    "config": {
      "size_hidden_layers": [
        16,
        8
      ],
      "input_dim": 9,
      "output_dim": 2,
      "activation": [
        "tanh",
        "sigmoid"
      ],
      "learning_rate": 0.01,
      "momentum": 0.0,
      "regularization": [
        "l2",
        1e-07
      ],
      "monitor": "Val_MEE",
      "early_stopping": [
        1e-05,
        200
      ],
      "weights_initialization": [
        "FanOut",
        0
      ],
      "max_epoch": 2000,
      "minibatch_size": 16,
      "decay": [
        "linear",
        0.1,
        8
      ]
    },
    "mean": 1.4838299751281738,
    "std": 0.0
  },
  {
    "config": {
      "size_hidden_layers": [
        16,
        8
      ],
      "input_dim": 9,
      "output_dim": 2,
      "activation": [
        "sigmoid",
        "tanh"
      ],
      "learning_rate": 0.001,
      "momentum": 0.8,
      "regularization": "none",
      "monitor": "Val_MEE",
      "early_stopping": [
        1e-05,
        200
      ],
      "weights_initialization": [
        "FanOut",
        0
      ],
      "max_epoch": 2000,
      "minibatch_size": 16,
      "decay": [
        "linear",
        0.1,
        8
      ]
    },
    "mean": 1.4839305877685547,
    "std": 0.0
  },
  {
    "config": {
      "size_hidden_layers": [
        16,
        8
      ],
      "input_dim": 9,
      "output_dim": 2,
      "activation": [
        "tanh",
        "sigmoid"
      ],
      "learning_rate": 0.01,
      "momentum": 0.0,
      "regularization": "none",
      "monitor": "Val_MEE",
      "early_stopping": [
        1e-05,
        200
      ],
      "weights_initialization": [
        "FanOut",
        0
      ],
      "max_epoch": 2000,
      "minibatch_size": 16,
      "decay": [
        "linear",
        0.1,
        8
      ]
    },
    "mean": 1.483931541442871,
    "std": 0.0
  },
  {
    "config": {
      "size_hidden_layers": [
        16,
        8
      ],
      "input_dim": 9,
      "output_dim": 2,
      "activation": [
        "tanh",
        "sigmoid"
      ],
      "learning_rate": 0.001,
      "momentum": 0.0,
      "regularization": [
        "l2",
        1e-06
      ],
      "monitor": "Val_MEE",
      "early_stopping": [
        1e-05,
        200
      ],
      "weights_initialization": [
        "FanOut",
        0
      ],
      "max_epoch": 2000,
      "minibatch_size": 8,
      "decay": [
        "linear",
        0.1,
        8
      ]
    },
    "mean": 1.4839366674423218,
    "std": 0.0
  },
  {
    "config": {
      "size_hidden_layers": [
        16,
        8
      ],
      "input_dim": 9,
      "output_dim": 2,
      "activation": [
        "tanh",
        "sigmoid"
      ],
      "learning_rate": 0.001,
      "momentum": 0.4,
      "regularization": [
        "l2",
        1e-06
      ],
      "monitor": "Val_MEE",
      "early_stopping": [
        1e-05,
        200
      ],
      "weights_initialization": [
        "FanOut",
        0
      ],
      "max_epoch": 2000,
      "minibatch_size": 8,
      "decay": "none"
    },
    "mean": 1.4839905500411987,
    "std": 0.0
  },
  {
    "config": {
      "size_hidden_layers": [
        16,
        8
      ],
      "input_dim": 9,
      "output_dim": 2,
      "activation": [
        "tanh",
        "sigmoid"
      ],
      "learning_rate": 0.001,
      "momentum": 0.4,
      "regularization": [
        "l2",
        1e-07
      ],
      "monitor": "Val_MEE",
      "early_stopping": [
        1e-05,
        200
      ],
      "weights_initialization": [
        "FanOut",
        0
      ],
      "max_epoch": 2000,
      "minibatch_size": 8,
      "decay": "none"
    },
    "mean": 1.4840285778045654,
    "std": 0.0
  },
  {
    "config": {
      "size_hidden_layers": [
        16,
        8
      ],
      "input_dim": 9,
      "output_dim": 2,
      "activation": [
        "tanh",
        "sigmoid"
      ],
      "learning_rate": 0.001,
      "momentum": 0.4,
      "regularization": "none",
      "monitor": "Val_MEE",
      "early_stopping": [
        1e-05,
        200
      ],
      "weights_initialization": [
        "FanOut",
        0
      ],
      "max_epoch": 2000,
      "minibatch_size": 8,
      "decay": "none"
    },
    "mean": 1.4840556383132935,
    "std": 0.0
  },
  {
    "config": {
      "size_hidden_layers": [
        16,
        8
      ],
      "input_dim": 9,
      "output_dim": 2,
      "activation": [
        "tanh",
        "sigmoid"
      ],
      "learning_rate": 0.01,
      "momentum": 0.0,
      "regularization": [
        "l2",
        1e-06
      ],
      "monitor": "Val_MEE",
      "early_stopping": [
        1e-05,
        200
      ],
      "weights_initialization": [
        "FanOut",
        0
      ],
      "max_epoch": 2000,
      "minibatch_size": 16,
      "decay": "none"
    },
    "mean": 1.4841893911361694,
    "std": 0.0
  },
  {
    "config": {
      "size_hidden_layers": [
        16,
        8
      ],
      "input_dim": 9,
      "output_dim": 2,
      "activation": [
        "sigmoid",
        "tanh"
      ],
      "learning_rate": 0.001,
      "momentum": 0.8,
      "regularization": [
        "l2",
        1e-07
      ],
      "monitor": "Val_MEE",
      "early_stopping": [
        1e-05,
        200
      ],
      "weights_initialization": [
        "FanOut",
        0
      ],
      "max_epoch": 2000,
      "minibatch_size": 16,
      "decay": [
        "linear",
        0.1,
        8
      ]
    },
    "mean": 1.4843302965164185,
    "std": 0.0
  },
  {
    "config": {
      "size_hidden_layers": [
        16,
        8
      ],
      "input_dim": 9,
      "output_dim": 2,
      "activation": [
        "tanh",
        "sigmoid"
      ],
      "learning_rate": 0.01,
      "momentum": 0.0,
      "regularization": [
        "l2",
        1e-07
      ],
      "monitor": "Val_MEE",
      "early_stopping": [
        1e-05,
        200
      ],
      "weights_initialization": [
        "FanOut",
        0
      ],
      "max_epoch": 2000,
      "minibatch_size": 16,
      "decay": "none"
    },
    "mean": 1.4847780466079712,
    "std": 0.0
  },
  {
    "config": {
      "size_hidden_layers": [
        16,
        8
      ],
      "input_dim": 9,
      "output_dim": 2,
      "activation": [
        "tanh",
        "sigmoid"
      ],
      "learning_rate": 0.01,
      "momentum": 0.0,
      "regularization": "none",
      "monitor": "Val_MEE",
      "early_stopping": [
        1e-05,
        200
      ],
      "weights_initialization": [
        "FanOut",
        0
      ],
      "max_epoch": 2000,
      "minibatch_size": 16,
      "decay": "none"
    },
    "mean": 1.4848859310150146,
    "std": 0.0
  },
  {
    "config": {
      "size_hidden_layers": [
        8,
        4
      ],
      "input_dim": 9,
      "output_dim": 2,
      "activation": [
        "sigmoid",
        "tanh"
      ],
      "learning_rate": 0.001,
      "momentum": 0.8,
      "regularization": "none",
      "monitor": "Val_MEE",
      "early_stopping": [
        1e-05,
        200
      ],
      "weights_initialization": [
        "FanOut",
        0
      ],
      "max_epoch": 2000,
      "minibatch_size": 8,
      "decay": [
        "linear",
        0.1,
        8
      ]
    },
    "mean": 1.484953761100769,
    "std": 0.0
  },
  {
    "config": {
      "size_hidden_layers": [
        8,
        4
      ],
      "input_dim": 9,
      "output_dim": 2,
      "activation": [
        "sigmoid",
        "tanh"
      ],
      "learning_rate": 0.001,
      "momentum": 0.8,
      "regularization": [
        "l2",
        1e-07
      ],
      "monitor": "Val_MEE",
      "early_stopping": [
        1e-05,
        200
      ],
      "weights_initialization": [
        "FanOut",
        0
      ],
      "max_epoch": 2000,
      "minibatch_size": 8,
      "decay": [
        "linear",
        0.1,
        8
      ]
    },
    "mean": 1.4850397109985352,
    "std": 0.0
  },
  {
    "config": {
      "size_hidden_layers": [
        16,
        8
      ],
      "input_dim": 9,
      "output_dim": 2,
      "activation": [
        "sigmoid",
        "tanh"
      ],
      "learning_rate": 0.001,
      "momentum": 0.4,
      "regularization": "none",
      "monitor": "Val_MEE",
      "early_stopping": [
        1e-05,
        200
      ],
      "weights_initialization": [
        "Uniform",
        -0.5,
        0.5,
        0
      ],
      "max_epoch": 2000,
      "minibatch_size": 8,
      "decay": [
        "linear",
        0.1,
        8
      ]
    },
    "mean": 1.4852732419967651,
    "std": 0.0
  },
  {
    "config": {
      "size_hidden_layers": [
        16,
        8
      ],
      "input_dim": 9,
      "output_dim": 2,
      "activation": [
        "sigmoid",
        "tanh"
      ],
      "learning_rate": 0.001,
      "momentum": 0.8,
      "regularization": [
        "l2",
        1e-06
      ],
      "monitor": "Val_MEE",
      "early_stopping": [
        1e-05,
        200
      ],
      "weights_initialization": [
        "FanOut",
        0
      ],
      "max_epoch": 2000,
      "minibatch_size": 16,
      "decay": "none"
    },
    "mean": 1.4853782653808594,
    "std": 0.0
  },
  {
    "config": {
      "size_hidden_layers": [
        8,
        8
      ],
      "input_dim": 9,
      "output_dim": 2,
      "activation": [
        "sigmoid",
        "tanh"
      ],
      "learning_rate": 0.01,
      "momentum": 0.8,
      "regularization": "none",
      "monitor": "Val_MEE",
      "early_stopping": [
        1e-05,
        200
      ],
      "weights_initialization": [
        "Uniform",
        -0.5,
        0.5,
        0
      ],
      "max_epoch": 2000,
      "minibatch_size": 16,
      "decay": "none"
    },
    "mean": 1.485538125038147,
    "std": 0.0
  },
  {
    "config": {
      "size_hidden_layers": [
        8,
        8
      ],
      "input_dim": 9,
      "output_dim": 2,
      "activation": [
        "sigmoid",
        "tanh"
      ],
      "learning_rate": 0.01,
      "momentum": 0.8,
      "regularization": [
        "l2",
        1e-07
      ],
      "monitor": "Val_MEE",
      "early_stopping": [
        1e-05,
        200
      ],
      "weights_initialization": [
        "Uniform",
        -0.5,
        0.5,
        0
      ],
      "max_epoch": 2000,
      "minibatch_size": 16,
      "decay": "none"
    },
    "mean": 1.4855610132217407,
    "std": 0.0
  },
  {
    "config": {
      "size_hidden_layers": [
        8,
        8
      ],
      "input_dim": 9,
      "output_dim": 2,
      "activation": "sigmoid",
      "learning_rate": 0.01,
      "momentum": 0.0,
      "regularization": [
        "l2",
        1e-07
      ],
      "monitor": "Val_MEE",
      "early_stopping": [
        1e-05,
        200
      ],
      "weights_initialization": [
        "Uniform",
        -0.5,
        0.5,
        0
      ],
      "max_epoch": 2000,
      "minibatch_size": 8,
      "decay": [
        "linear",
        0.1,
        8
      ]
    },
    "mean": 1.4856168031692505,
    "std": 0.0
  },
  {
    "config": {
      "size_hidden_layers": [
        16,
        8
      ],
      "input_dim": 9,
      "output_dim": 2,
      "activation": [
        "tanh",
        "sigmoid"
      ],
      "learning_rate": 0.01,
      "momentum": 0.4,
      "regularization": [
        "l2",
        1e-06
      ],
      "monitor": "Val_MEE",
      "early_stopping": [
        1e-05,
        200
      ],
      "weights_initialization": [
        "FanOut",
        0
      ],
      "max_epoch": 2000,
      "minibatch_size": 16,
      "decay": [
        "linear",
        0.1,
        8
      ]
    },
    "mean": 1.485695719718933,
    "std": 0.0
  },
  {
    "config": {
      "size_hidden_layers": [
        16,
        8
      ],
      "input_dim": 9,
      "output_dim": 2,
      "activation": [
        "sigmoid",
        "tanh"
      ],
      "learning_rate": 0.001,
      "momentum": 0.4,
      "regularization": [
        "l2",
        1e-07
      ],
      "monitor": "Val_MEE",
      "early_stopping": [
        1e-05,
        200
      ],
      "weights_initialization": [
        "Uniform",
        -0.5,
        0.5,
        0
      ],
      "max_epoch": 2000,
      "minibatch_size": 8,
      "decay": [
        "linear",
        0.1,
        8
      ]
    },
    "mean": 1.48582124710083,
    "std": 0.0
  },
  {
    "config": {
      "size_hidden_layers": [
        8,
        8
      ],
      "input_dim": 9,
      "output_dim": 2,
      "activation": "sigmoid",
      "learning_rate": 0.01,
      "momentum": 0.0,
      "regularization": "none",
      "monitor": "Val_MEE",
      "early_stopping": [
        1e-05,
        200
      ],
      "weights_initialization": [
        "Uniform",
        -0.5,
        0.5,
        0
      ],
      "max_epoch": 2000,
      "minibatch_size": 8,
      "decay": [
        "linear",
        0.1,
        8
      ]
    },
    "mean": 1.486021637916565,
    "std": 0.0
  },
  {
    "config": {
      "size_hidden_layers": [
        16,
        8
      ],
      "input_dim": 9,
      "output_dim": 2,
      "activation": [
        "tanh",
        "sigmoid"
      ],
      "learning_rate": 0.001,
      "momentum": 0.4,
      "regularization": [
        "l2",
        1e-06
      ],
      "monitor": "Val_MEE",
      "early_stopping": [
        1e-05,
        200
      ],
      "weights_initialization": [
        "FanOut",
        0
      ],
      "max_epoch": 2000,
      "minibatch_size": 8,
      "decay": [
        "linear",
        0.1,
        8
      ]
    },
    "mean": 1.4866054058074951,
    "std": 0.0
  },
  {
    "config": {
      "size_hidden_layers": [
        16,
        8
      ],
      "input_dim": 9,
      "output_dim": 2,
      "activation": [
        "tanh",
        "sigmoid"
      ],
      "learning_rate": 0.001,
      "momentum": 0.4,
      "regularization": [
        "l2",
        1e-06
      ],
      "monitor": "Val_MEE",
      "early_stopping": [
        1e-05,
        200
      ],
      "weights_initialization": [
        "FanOut",
        0
      ],
      "max_epoch": 2000,
      "minibatch_size": 16,
      "decay": "none"
    },
    "mean": 1.486656665802002,
    "std": 0.0
  },
  {
    "config": {
      "size_hidden_layers": [
        16,
        8
      ],
      "input_dim": 9,
      "output_dim": 2,
      "activation": [
        "tanh",
        "sigmoid"
      ],
      "learning_rate": 0.001,
      "momentum": 0.4,
      "regularization": [
        "l2",
        1e-07
      ],
      "monitor": "Val_MEE",
      "early_stopping": [
        1e-05,
        200
      ],
      "weights_initialization": [
        "FanOut",
        0
      ],
      "max_epoch": 2000,
      "minibatch_size": 8,
      "decay": [
        "linear",
        0.1,
        8
      ]
    },
    "mean": 1.4867268800735474,
    "std": 0.0
  },
  {
    "config": {
      "size_hidden_layers": [
        16,
        8
      ],
      "input_dim": 9,
      "output_dim": 2,
      "activation": [
        "tanh",
        "sigmoid"
      ],
      "learning_rate": 0.001,
      "momentum": 0.4,
      "regularization": "none",
      "monitor": "Val_MEE",
      "early_stopping": [
        1e-05,
        200
      ],
      "weights_initialization": [
        "FanOut",
        0
      ],
      "max_epoch": 2000,
      "minibatch_size": 8,
      "decay": [
        "linear",
        0.1,
        8
      ]
    },
    "mean": 1.486811637878418,
    "std": 0.0
  },
  {
    "config": {
      "size_hidden_layers": [
        16,
        8
      ],
      "input_dim": 9,
      "output_dim": 2,
      "activation": [
        "sigmoid",
        "tanh"
      ],
      "learning_rate": 0.001,
      "momentum": 0.8,
      "regularization": [
        "l2",
        1e-06
      ],
      "monitor": "Val_MEE",
      "early_stopping": [
        1e-05,
        200
      ],
      "weights_initialization": [
        "FanOut",
        0
      ],
      "max_epoch": 2000,
      "minibatch_size": 16,
      "decay": [
        "linear",
        0.1,
        8
      ]
    },
    "mean": 1.486917495727539,
    "std": 0.0
  },
  {
    "config": {
      "size_hidden_layers": [
        16,
        8
      ],
      "input_dim": 9,
      "output_dim": 2,
      "activation": [
        "tanh",
        "sigmoid"
      ],
      "learning_rate": 0.001,
      "momentum": 0.4,
      "regularization": "none",
      "monitor": "Val_MEE",
      "early_stopping": [
        1e-05,
        200
      ],
      "weights_initialization": [
        "FanOut",
        0
      ],
      "max_epoch": 2000,
      "minibatch_size": 16,
      "decay": "none"
    },
    "mean": 1.4871406555175781,
    "std": 0.0
  },
  {
    "config": {
      "size_hidden_layers": [
        16,
        8
      ],
      "input_dim": 9,
      "output_dim": 2,
      "activation": [
        "tanh",
        "sigmoid"
      ],
      "learning_rate": 0.001,
      "momentum": 0.4,
      "regularization": [
        "l2",
        1e-07
      ],
      "monitor": "Val_MEE",
      "early_stopping": [
        1e-05,
        200
      ],
      "weights_initialization": [
        "FanOut",
        0
      ],
      "max_epoch": 2000,
      "minibatch_size": 16,
      "decay": "none"
    },
    "mean": 1.487145185470581,
    "std": 0.0
  },
  {
    "config": {
      "size_hidden_layers": [
        16,
        8
      ],
      "input_dim": 9,
      "output_dim": 2,
      "activation": [
        "tanh",
        "sigmoid"
      ],
      "learning_rate": 0.01,
      "momentum": 0.4,
      "regularization": [
        "l2",
        1e-06
      ],
      "monitor": "Val_MEE",
      "early_stopping": [
        1e-05,
        200
      ],
      "weights_initialization": [
        "FanOut",
        0
      ],
      "max_epoch": 2000,
      "minibatch_size": 16,
      "decay": "none"
    },
    "mean": 1.487393856048584,
    "std": 0.0
  },
  {
    "config": {
      "size_hidden_layers": [
        16,
        8
      ],
      "input_dim": 9,
      "output_dim": 2,
      "activation": [
        "sigmoid",
        "tanh"
      ],
      "learning_rate": 0.001,
      "momentum": 0.4,
      "regularization": "none",
      "monitor": "Val_MEE",
      "early_stopping": [
        1e-05,
        200
      ],
      "weights_initialization": [
        "Uniform",
        -0.5,
        0.5,
        0
      ],
      "max_epoch": 2000,
      "minibatch_size": 8,
      "decay": "none"
    },
    "mean": 1.487708330154419,
    "std": 0.0
  },
  {
    "config": {
      "size_hidden_layers": [
        16,
        8
      ],
      "input_dim": 9,
      "output_dim": 2,
      "activation": [
        "tanh",
        "sigmoid"
      ],
      "learning_rate": 0.01,
      "momentum": 0.0,
      "regularization": [
        "l2",
        1e-07
      ],
      "monitor": "Val_MEE",
      "early_stopping": [
        1e-05,
        200
      ],
      "weights_initialization": [
        "FanOut",
        0
      ],
      "max_epoch": 2000,
      "minibatch_size": 8,
      "decay": [
        "linear",
        0.1,
        8
      ]
    },
    "mean": 1.4879989624023438,
    "std": 0.0
  },
  {
    "config": {
      "size_hidden_layers": [
        16,
        8
      ],
      "input_dim": 9,
      "output_dim": 2,
      "activation": [
        "sigmoid",
        "tanh"
      ],
      "learning_rate": 0.001,
      "momentum": 0.4,
      "regularization": [
        "l2",
        1e-07
      ],
      "monitor": "Val_MEE",
      "early_stopping": [
        1e-05,
        200
      ],
      "weights_initialization": [
        "Uniform",
        -0.5,
        0.5,
        0
      ],
      "max_epoch": 2000,
      "minibatch_size": 8,
      "decay": "none"
    },
    "mean": 1.4881742000579834,
    "std": 0.0
  },
  {
    "config": {
      "size_hidden_layers": [
        16,
        8
      ],
      "input_dim": 9,
      "output_dim": 2,
      "activation": [
        "tanh",
        "sigmoid"
      ],
      "learning_rate": 0.01,
      "momentum": 0.0,
      "regularization": "none",
      "monitor": "Val_MEE",
      "early_stopping": [
        1e-05,
        200
      ],
      "weights_initialization": [
        "FanOut",
        0
      ],
      "max_epoch": 2000,
      "minibatch_size": 8,
      "decay": [
        "linear",
        0.1,
        8
      ]
    },
    "mean": 1.4885848760604858,
    "std": 0.0
  },
  {
    "config": {
      "size_hidden_layers": [
        16,
        8
      ],
      "input_dim": 9,
      "output_dim": 2,
      "activation": [
        "sigmoid",
        "tanh"
      ],
      "learning_rate": 0.001,
      "momentum": 0.0,
      "regularization": "none",
      "monitor": "Val_MEE",
      "early_stopping": [
        1e-05,
        200
      ],
      "weights_initialization": [
        "Uniform",
        -0.5,
        0.5,
        0
      ],
      "max_epoch": 2000,
      "minibatch_size": 8,
      "decay": "none"
    },
    "mean": 1.4886022806167603,
    "std": 0.0
  },
  {
    "config": {
      "size_hidden_layers": [
        16,
        8
      ],
      "input_dim": 9,
      "output_dim": 2,
      "activation": [
        "sigmoid",
        "tanh"
      ],
      "learning_rate": 0.001,
      "momentum": 0.0,
      "regularization": [
        "l2",
        1e-07
      ],
      "monitor": "Val_MEE",
      "early_stopping": [
        1e-05,
        200
      ],
      "weights_initialization": [
        "Uniform",
        -0.5,
        0.5,
        0
      ],
      "max_epoch": 2000,
      "minibatch_size": 8,
      "decay": "none"
    },
    "mean": 1.4886786937713623,
    "std": 0.0
  },
  {
    "config": {
      "size_hidden_layers": [
        16,
        8
      ],
      "input_dim": 9,
      "output_dim": 2,
      "activation": [
        "tanh",
        "sigmoid"
      ],
      "learning_rate": 0.001,
      "momentum": 0.8,
      "regularization": [
        "l2",
        1e-06
      ],
      "monitor": "Val_MEE",
      "early_stopping": [
        1e-05,
        200
      ],
      "weights_initialization": [
        "FanOut",
        0
      ],
      "max_epoch": 2000,
      "minibatch_size": 8,
      "decay": "none"
    },
    "mean": 1.488728404045105,
    "std": 0.0
  },
  {
    "config": {
      "size_hidden_layers": [
        16,
        8
      ],
      "input_dim": 9,
      "output_dim": 2,
      "activation": "sigmoid",
      "learning_rate": 0.01,
      "momentum": 0.8,
      "regularization": "none",
      "monitor": "Val_MEE",
      "early_stopping": [
        1e-05,
        200
      ],
      "weights_initialization": [
        "FanOut",
        0
      ],
      "max_epoch": 2000,
      "minibatch_size": 16,
      "decay": [
        "linear",
        0.1,
        8
      ]
    },
    "mean": 1.4887731075286865,
    "std": 0.0
  },
  {
    "config": {
      "size_hidden_layers": [
        16,
        8
      ],
      "input_dim": 9,
      "output_dim": 2,
      "activation": "sigmoid",
      "learning_rate": 0.01,
      "momentum": 0.8,
      "regularization": [
        "l2",
        1e-07
      ],
      "monitor": "Val_MEE",
      "early_stopping": [
        1e-05,
        200
      ],
      "weights_initialization": [
        "FanOut",
        0
      ],
      "max_epoch": 2000,
      "minibatch_size": 16,
      "decay": [
        "linear",
        0.1,
        8
      ]
    },
    "mean": 1.488827109336853,
    "std": 0.0
  },
  {
    "config": {
      "size_hidden_layers": [
        16,
        8
      ],
      "input_dim": 9,
      "output_dim": 2,
      "activation": "sigmoid",
      "learning_rate": 0.01,
      "momentum": 0.8,
      "regularization": "none",
      "monitor": "Val_MEE",
      "early_stopping": [
        1e-05,
        200
      ],
      "weights_initialization": [
        "FanOut",
        0
      ],
      "max_epoch": 2000,
      "minibatch_size": 16,
      "decay": "none"
    },
    "mean": 1.489187240600586,
    "std": 0.0
  },
  {
    "config": {
      "size_hidden_layers": [
        16,
        8
      ],
      "input_dim": 9,
      "output_dim": 2,
      "activation": "sigmoid",
      "learning_rate": 0.01,
      "momentum": 0.8,
      "regularization": [
        "l2",
        1e-07
      ],
      "monitor": "Val_MEE",
      "early_stopping": [
        1e-05,
        200
      ],
      "weights_initialization": [
        "FanOut",
        0
      ],
      "max_epoch": 2000,
      "minibatch_size": 16,
      "decay": "none"
    },
    "mean": 1.489245891571045,
    "std": 0.0
  },
  {
    "config": {
      "size_hidden_layers": [
        16,
        8
      ],
      "input_dim": 9,
      "output_dim": 2,
      "activation": "sigmoid",
      "learning_rate": 0.01,
      "momentum": 0.8,
      "regularization": [
        "l2",
        1e-06
      ],
      "monitor": "Val_MEE",
      "early_stopping": [
        1e-05,
        200
      ],
      "weights_initialization": [
        "FanOut",
        0
      ],
      "max_epoch": 2000,
      "minibatch_size": 16,
      "decay": [
        "linear",
        0.1,
        8
      ]
    },
    "mean": 1.4892898797988892,
    "std": 0.0
  },
  {
    "config": {
      "size_hidden_layers": [
        8,
        8
      ],
      "input_dim": 9,
      "output_dim": 2,
      "activation": [
        "tanh",
        "sigmoid"
      ],
      "learning_rate": 0.001,
      "momentum": 0.4,
      "regularization": [
        "l2",
        1e-06
      ],
      "monitor": "Val_MEE",
      "early_stopping": [
        1e-05,
        200
      ],
      "weights_initialization": [
        "FanOut",
        0
      ],
      "max_epoch": 2000,
      "minibatch_size": 8,
      "decay": "none"
    },
    "mean": 1.4893463850021362,
    "std": 0.0
  },
  {
    "config": {
      "size_hidden_layers": [
        16,
        8
      ],
      "input_dim": 9,
      "output_dim": 2,
      "activation": [
        "sigmoid",
        "tanh"
      ],
      "learning_rate": 0.001,
      "momentum": 0.4,
      "regularization": [
        "l2",
        1e-06
      ],
      "monitor": "Val_MEE",
      "early_stopping": [
        1e-05,
        200
      ],
      "weights_initialization": [
        "Uniform",
        -0.5,
        0.5,
        0
      ],
      "max_epoch": 2000,
      "minibatch_size": 8,
      "decay": "none"
    },
    "mean": 1.4895251989364624,
    "std": 0.0
  },
  {
    "config": {
      "size_hidden_layers": [
        16,
        8
      ],
      "input_dim": 9,
      "output_dim": 2,
      "activation": "tanh",
      "learning_rate": 0.001,
      "momentum": 0.8,
      "regularization": [
        "l2",
        1e-06
      ],
      "monitor": "Val_MEE",
      "early_stopping": [
        1e-05,
        200
      ],
      "weights_initialization": [
        "Uniform",
        -0.5,
        0.5,
        0
      ],
      "max_epoch": 2000,
      "minibatch_size": 16,
      "decay": [
        "linear",
        0.1,
        8
      ]
    },
    "mean": 1.489717721939087,
    "std": 0.0
  },
  {
    "config": {
      "size_hidden_layers": [
        16,
        8
      ],
      "input_dim": 9,
      "output_dim": 2,
      "activation": "sigmoid",
      "learning_rate": 0.01,
      "momentum": 0.8,
      "regularization": [
        "l2",
        1e-06
      ],
      "monitor": "Val_MEE",
      "early_stopping": [
        1e-05,
        200
      ],
      "weights_initialization": [
        "FanOut",
        0
      ],
      "max_epoch": 2000,
      "minibatch_size": 16,
      "decay": "none"
    },
    "mean": 1.4897464513778687,
    "std": 0.0
  },
  {
    "config": {
      "size_hidden_layers": [
        16,
        8
      ],
      "input_dim": 9,
      "output_dim": 2,
      "activation": [
        "tanh",
        "sigmoid"
      ],
      "learning_rate": 0.001,
      "momentum": 0.4,
      "regularization": [
        "l2",
        1e-06
      ],
      "monitor": "Val_MEE",
      "early_stopping": [
        1e-05,
        200
      ],
      "weights_initialization": [
        "FanOut",
        0
      ],
      "max_epoch": 2000,
      "minibatch_size": 16,
      "decay": [
        "linear",
        0.1,
        8
      ]
    },
    "mean": 1.4899523258209229,
    "std": 0.0
  }
]